InvoiceOcrGubs_3/__init__.py
InvoiceOcrGubs_3/final.py
InvoiceOcrGubs_3/part1.py
InvoiceOcrGubs_3/part3.py
GUBS_Invoice_OCR-0.0.0.2.dist-info/LICENSE
GUBS_Invoice_OCR-0.0.0.2.dist-info/METADATA
GUBS_Invoice_OCR-0.0.0.2.dist-info/WHEEL
GUBS_Invoice_OCR-0.0.0.2.dist-info/top_level.txt
GUBS_Invoice_OCR-0.0.0.2.dist-info/RECORD
