Metadata-Version: 2.1
Name: GUBS-Invoice-OCR
Version: 0.0.0.2
Summary: An invoice ocr package
Home-page: https://bitbucket.org/shubh1993/textextractionpython
Author: Gurukul_Bytes
Author-email: dev.gurukulbytes@gmail.com
Classifier: Programming Language :: Python :: 3
Classifier: License :: OSI Approved :: MIT License
Classifier: Operating System :: OS Independent
Requires-Python: >=3.6
License-File: LICENSE
